cognee/__init__.py
cognee/__main__.py
cognee/base_config.py
cognee/context_global_variables.py
cognee/get_token.py
cognee/low_level.py
cognee/pipelines.py
cognee/root_dir.py
cognee/version.py
cognee/api/.env.example
cognee/api/DTO.py
cognee/api/__init__.py
cognee/api/client.py
cognee/api/health.py
cognee/api/v1/__init__.py
cognee/api/v1/add/__init__.py
cognee/api/v1/add/add.py
cognee/api/v1/add/routers/__init__.py
cognee/api/v1/add/routers/get_add_router.py
cognee/api/v1/cloud/routers/__init__.py
cognee/api/v1/cloud/routers/get_checks_router.py
cognee/api/v1/cognify/__init__.py
cognee/api/v1/cognify/cognify.py
cognee/api/v1/cognify/routers/__init__.py
cognee/api/v1/cognify/routers/get_cognify_router.py
cognee/api/v1/config/__init__.py
cognee/api/v1/config/config.py
cognee/api/v1/datasets/__init__.py
cognee/api/v1/datasets/datasets.py
cognee/api/v1/datasets/routers/__init__.py
cognee/api/v1/datasets/routers/get_datasets_router.py
cognee/api/v1/delete/__init__.py
cognee/api/v1/delete/delete.py
cognee/api/v1/delete/routers/__init__.py
cognee/api/v1/delete/routers/get_delete_router.py
cognee/api/v1/exceptions/__init__.py
cognee/api/v1/exceptions/exceptions.py
cognee/api/v1/memify/__init__.py
cognee/api/v1/memify/routers/__init__.py
cognee/api/v1/memify/routers/get_memify_router.py
cognee/api/v1/notebooks/routers/__init__.py
cognee/api/v1/notebooks/routers/get_notebooks_router.py
cognee/api/v1/ontologies/__init__.py
cognee/api/v1/ontologies/ontologies.py
cognee/api/v1/ontologies/routers/__init__.py
cognee/api/v1/ontologies/routers/get_ontology_router.py
cognee/api/v1/permissions/routers/__init__.py
cognee/api/v1/permissions/routers/get_permissions_router.py
cognee/api/v1/prune/__init__.py
cognee/api/v1/prune/prune.py
cognee/api/v1/responses/__init__.py
cognee/api/v1/responses/default_tools.py
cognee/api/v1/responses/dispatch_function.py
cognee/api/v1/responses/models.py
cognee/api/v1/responses/routers/__init__.py
cognee/api/v1/responses/routers/default_tools.py
cognee-0.5.1.dist-info/METADATA
cognee-0.5.1.dist-info/WHEEL
cognee-0.5.1.dist-info/entry_points.txt
cognee-0.5.1.dist-info/licenses/LICENSE
cognee-0.5.1.dist-info/licenses/NOTICE.md
cognee-0.5.1.dist-info/RECORD
