Metadata-Version: 2.4
Name: cognee
Version: 0.5.1
Summary: Cognee - is a library for enriching LLM context with a semantic layer for better understanding and reasoning.
Project-URL: Homepage, https://www.cognee.ai
Project-URL: Repository, https://github.com/topoteretes/cognee
Author: Vasilije Markovic, Boris Arzentar
License-Expression: Apache-2.0
License-File: LICENSE
License-File: NOTICE.md
Classifier: Development Status :: 4 - Beta
Classifier: Intended Audience :: Developers
Classifier: License :: OSI Approved :: Apache Software License
Classifier: Operating System :: MacOS :: MacOS X
Classifier: Operating System :: Microsoft :: Windows
Classifier: Operating System :: POSIX :: Linux
Classifier: Topic :: Software Development :: Libraries
Requires-Python: <3.14,>=3.10
Requires-Dist: aiofiles>=23.2.1
Requires-Dist: aiohttp<4.0.0,>=3.11.14
Requires-Dist: aiolimiter>=1.2.1
Requires-Dist: aiosqlite<1.0.0,>=0.20.0
Requires-Dist: alembic<2,>=1.13.3
Requires-Dist: diskcache>=5.6.3
Requires-Dist: fakeredis[lua]>=2.32.0
Requires-Dist: fastapi-users[sqlalchemy]<15.0.0,>=14.0.1
Requires-Dist: fastapi<1.0.0,>=0.116.2
Requires-Dist: fastembed<=0.6.0
Requires-Dist: filetype<2.0.0,>=1.2.0
Requires-Dist: gunicorn<24,>=20.1.0
Requires-Dist: instructor<2.0.0,>=1.9.1
Requires-Dist: jinja2<4,>=3.1.3
Requires-Dist: kuzu==0.11.3
Requires-Dist: lancedb<1.0.0,>=0.24.0
Requires-Dist: limits<5,>=4.4.1
Requires-Dist: litellm>=1.76.0
Requires-Dist: mistralai>=1.9.10
Requires-Dist: nbformat<6.0.0,>=5.7.0
Requires-Dist: networkx<4,>=3.4.2
Requires-Dist: numpy<=4.0.0,>=1.26.4
Requires-Dist: onnxruntime<=1.22.1
Requires-Dist: openai>=1.80.1
Requires-Dist: pydantic-settings<3,>=2.2.1
Requires-Dist: pydantic<2.12.0,>=2.10.5
Requires-Dist: pylance<=0.36.0,>=0.22.0
Requires-Dist: pympler<2.0.0,>=1.1
Requires-Dist: pypdf<7.0.0,>=4.1.0
Requires-Dist: python-dotenv<2.0.0,>=1.0.1
Requires-Dist: python-magic-bin<0.5; platform_system == 'Windows'
Requires-Dist: python-multipart<1.0.0,>=0.0.20
Requires-Dist: rdflib<7.2.0,>=7.1.4
Requires-Dist: sqlalchemy<3.0.0,>=2.0.39
Requires-Dist: structlog<26,>=25.2.0
Requires-Dist: tenacity>=9.0.0
Requires-Dist: tiktoken<1.0.0,>=0.8.0
Requires-Dist: typing-extensions<5.0.0,>=4.12.2
Requires-Dist: uvicorn<1.0.0,>=0.34.0
Requires-Dist: websockets<16.0.0,>=15.0.1
Provides-Extra: anthropic
Requires-Dist: anthropic>=0.27; extra == 'anthropic'
Provides-Extra: api
Provides-Extra: aws
Requires-Dist: s3fs[boto3]==2025.3.2; extra == 'aws'
Provides-Extra: baml
Requires-Dist: baml-py==0.206.0; extra == 'baml'
Provides-Extra: chromadb
Requires-Dist: chromadb<0.7,>=0.6; extra == 'chromadb'
Requires-Dist: pypika==0.48.9; extra == 'chromadb'
Provides-Extra: codegraph
Requires-Dist: fastembed<=0.6.0; (python_version < '3.13') and extra == 'codegraph'
Requires-Dist: transformers<5,>=4.46.3; extra == 'codegraph'
Requires-Dist: tree-sitter-python<0.24,>=0.23.6; extra == 'codegraph'
Requires-Dist: tree-sitter<0.25,>=0.24.0; extra == 'codegraph'
Provides-Extra: debug
Requires-Dist: debugpy<2.0.0,>=1.8.9; extra == 'debug'
Provides-Extra: deepeval
Requires-Dist: deepeval<4,>=3.0.1; extra == 'deepeval'
Provides-Extra: dev
Requires-Dist: coverage<8,>=7.3.2; extra == 'dev'
Requires-Dist: deptry<0.21,>=0.20.0; extra == 'dev'
Requires-Dist: gitpython<4,>=3.1.43; extra == 'dev'
Requires-Dist: mkdocs-material<10,>=9.5.42; extra == 'dev'
Requires-Dist: mkdocs-minify-plugin<0.9,>=0.8.0; extra == 'dev'
Requires-Dist: mkdocstrings[python]<0.27,>=0.26.2; extra == 'dev'
Requires-Dist: mypy<2,>=1.7.1; extra == 'dev'
Requires-Dist: notebook<8,>=7.1.0; extra == 'dev'
Requires-Dist: pre-commit<5,>=4.0.1; extra == 'dev'
Requires-Dist: pylint<4,>=3.0.3; extra == 'dev'
Requires-Dist: pytest-asyncio<0.22,>=0.21.1; extra == 'dev'
Requires-Dist: pytest-cov<7.0.0,>=6.1.1; extra == 'dev'
Requires-Dist: pytest<8,>=7.4.0; extra == 'dev'
Requires-Dist: ruff<=0.13.1,>=0.9.2; extra == 'dev'
Requires-Dist: tweepy<5.0.0,>=4.14.0; extra == 'dev'
Provides-Extra: distributed
Requires-Dist: modal<2.0.0,>=1.0.5; extra == 'distributed'
Provides-Extra: dlt
Requires-Dist: dlt[sqlalchemy]<2,>=1.9.0; extra == 'dlt'
Provides-Extra: docling
Requires-Dist: docling>=2.54; extra == 'docling'
Requires-Dist: transformers>=4.55; extra == 'docling'
Provides-Extra: docs
Requires-Dist: lxml<5,>=4.9.3; (python_version < '3.13') and extra == 'docs'
Requires-Dist: lxml<6,>=5; (python_version >= '3.13') and extra == 'docs'
Requires-Dist: unstructured[csv,doc,docx,epub,md,odt,org,pdf,ppt,pptx,rst,rtf,tsv,xlsx]<19,>=0.18.1; extra == 'docs'
Provides-Extra: evals
Requires-Dist: gdown<6,>=5.2.0; extra == 'evals'
Requires-Dist: matplotlib<4,>=3.8.3; extra == 'evals'
Requires-Dist: pandas<3.0.0,>=2.2.2; extra == 'evals'
Requires-Dist: plotly<7,>=6.0.0; extra == 'evals'
Requires-Dist: scikit-learn<2,>=1.6.1; extra == 'evals'
Provides-Extra: graphiti
Requires-Dist: graphiti-core<0.8,>=0.7.0; extra == 'graphiti'
Provides-Extra: groq
Requires-Dist: groq<1.0.0,>=0.8.0; extra == 'groq'
Provides-Extra: huggingface
Requires-Dist: transformers<5,>=4.46.3; extra == 'huggingface'
Provides-Extra: langchain
Requires-Dist: langchain-text-splitters<1.0.0,>=0.3.2; extra == 'langchain'
Requires-Dist: langsmith<1.0.0,>=0.2.3; extra == 'langchain'
Provides-Extra: llama-index
Requires-Dist: llama-index-core<0.13,>=0.12.11; extra == 'llama-index'
Provides-Extra: mistral
Requires-Dist: mistral-common<2,>=1.5.2; extra == 'mistral'
Provides-Extra: monitoring
Requires-Dist: langfuse<3,>=2.32.0; extra == 'monitoring'
Requires-Dist: sentry-sdk[fastapi]<3,>=2.9.0; extra == 'monitoring'
Provides-Extra: neo4j
Requires-Dist: neo4j<6,>=5.28.0; extra == 'neo4j'
Provides-Extra: neptune
Requires-Dist: langchain-aws>=0.2.22; extra == 'neptune'
Provides-Extra: notebook
Requires-Dist: notebook<8,>=7.1.0; extra == 'notebook'
Provides-Extra: ollama
Requires-Dist: transformers<5,>=4.46.3; extra == 'ollama'
Provides-Extra: postgres
Requires-Dist: asyncpg<1.0.0,>=0.30.0; extra == 'postgres'
Requires-Dist: pgvector<0.4,>=0.3.5; extra == 'postgres'
Requires-Dist: psycopg2<3,>=2.9.10; extra == 'postgres'
Provides-Extra: postgres-binary
Requires-Dist: asyncpg<1.0.0,>=0.30.0; extra == 'postgres-binary'
Requires-Dist: pgvector<0.4,>=0.3.5; extra == 'postgres-binary'
Requires-Dist: psycopg2-binary<3.0.0,>=2.9.10; extra == 'postgres-binary'
Provides-Extra: posthog
Requires-Dist: posthog<4,>=3.5.0; extra == 'posthog'
Provides-Extra: redis
Requires-Dist: redis<6.0.0,>=5.0.3; extra == 'redis'
Provides-Extra: scraping
Requires-Dist: apscheduler<=3.11.0,>=3.10.0; extra == 'scraping'
Requires-Dist: beautifulsoup4>=4.13.1; extra == 'scraping'
Requires-Dist: lxml<5,>=4.9.3; (python_version < '3.13') and extra == 'scraping'
Requires-Dist: lxml<6,>=5; (python_version >= '3.13') and extra == 'scraping'
Requires-Dist: playwright>=1.9.0; extra == 'scraping'
Requires-Dist: protego>=0.1; extra == 'scraping'
Requires-Dist: tavily-python>=0.7.12; extra == 'scraping'
